{
  "symbol": "GBPAUD",
  "optimized_at": "2026-06-29T23:41:33.533225",
  "train_summary": {
    "symbol": "GBPAUD",
    "trades": 853,
    "win_rate": 0.47245017584994137,
    "total_pnl": 500.16845109374503,
    "max_drawdown": 0.09236471838956141,
    "profit_factor": 1.5565720854162761,
    "wf_score": 1859.8000806813902,
    "wf_windows": 4
  },
  "test_summary": {
    "symbol": "GBPAUD",
    "trades": 580,
    "win_rate": 0.5051724137931034,
    "total_pnl": 718.2256634374928,
    "avg_win": 4.18053746693684,
    "avg_loss": -1.7654070187282287,
    "max_drawdown": 0.0804837198794601,
    "profit_factor": 2.417536249423012,
    "tp_count": 125,
    "sl_count": 455,
    "be_trail_count": 0,
    "final_balance": 1718.2256634374928
  },
  "params": {
    "_comment": "Kockázatmentesítés és trailing stop beállításai",
    "sma_period": 160,
    "wpr_m15_period": 32,
    "wpr_m1_period": 3,
    "_comment_levels": "WPR szintek: extrém zónák és trigger szint",
    "wpr_m15_sell_extreme": -30,
    "wpr_m15_buy_extreme": -70,
    "wpr_m15_trigger": -50,
    "wpr_m1_sell_extreme": -35,
    "wpr_m1_buy_extreme": -70,
    "wpr_m1_trigger": -55,
    "atr_period": 15,
    "sl_atr_mult": 1.5,
    "tp_rr_ratio": 2.75,
    "_comment_be": "breakeven_pct: a TP hány %-ánál toljuk az SL-t az entry szintre (0 = kikapcs)",
    "breakeven_pct": 0.3,
    "_comment_trail": "trail_activation_pips: ennyi pip profit UTÁN indul a trailing. trail_distance_pips: ennyivel követ",
    "trail_activation_pips": 20,
    "trail_distance_pips": 15,
    "max_open_slots": 6,
    "max_spread_atr_ratio": 0.25,
    "atr_min_pct": 0.6000000000000001,
    "atr_max_pct": 3.4000000000000004,
    "trade_hour_start": 10,
    "trade_hour_end": 13,
    "skip_monday_hours": 4,
    "skip_friday_hour": 20
  }
}